bct/__init__.py
bct/citations.py
bct/due.py
bct/nbs.py
bct/version.py
bct/algorithms/__init__.py
bct/algorithms/centrality.py
bct/algorithms/clustering.py
bct/algorithms/core.py
bct/algorithms/degree.py
bct/algorithms/distance.py
bct/algorithms/efficiency.py
bct/algorithms/generative.py
bct/algorithms/models.py
bct/algorithms/modularity.py
bct/algorithms/motifs.py
bct/algorithms/physical_connectivity.py
bct/algorithms/reference.py
bct/algorithms/similarity.py
bct/utils/__init__.py
bct/utils/miscellaneous_utilities.py
bct/utils/other.py
bct/utils/visualization.py
bctpy-0.6.0.dist-info/LICENSE
bctpy-0.6.0.dist-info/METADATA
bctpy-0.6.0.dist-info/WHEEL
bctpy-0.6.0.dist-info/top_level.txt
bctpy-0.6.0.dist-info/RECORD
