Metadata-Version: 2.1
Name: bctpy
Version: 0.6.0
Summary: Brain Connectivity Toolbox for Python
Home-page: https://github.com/aestrivex/bctpy
Maintainer: Roan LaPlante
Maintainer-email: rlaplant@nmr.mgh.harvard.edu
License: Visuddhimagga Sutta; GPLv3+
Platform: any
Classifier: Development Status :: 4 - Beta
Classifier: Environment :: X11 Applications
Classifier: Intended Audience :: Science/Research
Classifier: License :: OSI Approved :: GNU General Public License v3 or later (GPLv3+)
Classifier: Natural Language :: English
Classifier: Programming Language :: Python :: 2.7
Classifier: Programming Language :: Python :: 3.5
Classifier: Programming Language :: Python :: 3.6
Classifier: Programming Language :: Python :: 3.7
Classifier: Topic :: Scientific/Engineering :: Information Analysis
License-File: LICENSE
Requires-Dist: numpy
Requires-Dist: scipy
